voxcity/__init__.py
voxcity/downloader/__init__.py
voxcity/downloader/citygml.py
voxcity/downloader/eubucco.py
voxcity/downloader/gba.py
voxcity/downloader/gee.py
voxcity/downloader/mbfp.py
voxcity/downloader/ocean.py
voxcity/downloader/oemj.py
voxcity/downloader/osm.py
voxcity/downloader/overture.py
voxcity/downloader/utils.py
voxcity/errors.py
voxcity/exporter/__init__.py
voxcity/exporter/cityles.py
voxcity/exporter/envimet.py
voxcity/exporter/magicavoxel.py
voxcity/exporter/netcdf.py
voxcity/exporter/obj.py
voxcity/generator/__init__.py
voxcity/generator/api.py
voxcity/generator/grids.py
voxcity/generator/io.py
voxcity/generator/pipeline.py
voxcity/generator/update.py
voxcity/generator/voxelizer.py
voxcity/geoprocessor/__init__.py
voxcity/geoprocessor/conversion.py
voxcity/geoprocessor/draw.py
voxcity/geoprocessor/heights.py
voxcity/geoprocessor/io.py
voxcity/geoprocessor/merge_utils.py
voxcity/geoprocessor/mesh.py
voxcity/geoprocessor/network.py
voxcity/geoprocessor/overlap.py
voxcity/geoprocessor/raster/__init__.py
voxcity/geoprocessor/raster/buildings.py
voxcity/geoprocessor/raster/canopy.py
voxcity/geoprocessor/raster/core.py
voxcity/geoprocessor/raster/export.py
voxcity/geoprocessor/raster/landcover.py
voxcity/geoprocessor/raster/raster.py
voxcity/geoprocessor/selection.py
voxcity/geoprocessor/utils.py
voxcity/models.py
voxcity/simulator/__init__.py
voxcity/simulator/common/__init__.py
voxcity/simulator/common/geometry.py
voxcity/simulator/common/raytracing.py
voxcity/simulator/solar/__init__.py
voxcity/simulator/solar/integration.py
voxcity/simulator/solar/kernels.py
voxcity/simulator/solar/radiation.py
voxcity/simulator/solar/sky.py
voxcity/simulator/solar/temporal.py
voxcity/simulator/utils.py
voxcity/simulator/view.py
voxcity/simulator/visibility/__init__.py
voxcity/simulator/visibility/landmark.py
voxcity/simulator/visibility/view.py
voxcity/simulator_gpu/__init__.py
voxcity/simulator_gpu/core.py
voxcity/simulator_gpu/domain.py
voxcity-1.0.21.dist-info/licenses/AUTHORS.rst
voxcity-1.0.21.dist-info/licenses/LICENSE
voxcity-1.0.21.dist-info/METADATA
voxcity-1.0.21.dist-info/WHEEL
voxcity-1.0.21.dist-info/RECORD
