Metadata-Version: 2.4
Name: voxcity
Version: 1.0.21
Summary: voxcity is an easy and one-stop tool to output 3d city models for microclimate simulation by integrating multiple geospatial open-data
License: MIT
License-File: AUTHORS.rst
License-File: LICENSE
Author: Kunihiko Fujiwara
Author-email: fujiwara.kunihiko@takenaka.co.jp
Maintainer: Kunihiko Fujiwara
Maintainer-email: fujiwara.kunihiko@takenaka.co.jp
Requires-Python: >=3.10,<3.13
Classifier: License :: OSI Approved :: MIT License
Classifier: Programming Language :: Python :: 3
Classifier: Programming Language :: Python :: 3.10
Classifier: Programming Language :: Python :: 3.11
Classifier: Programming Language :: Python :: 3.12
Provides-Extra: gpu
Requires-Dist: IPython
Requires-Dist: affine
Requires-Dist: astral
Requires-Dist: contextily
Requires-Dist: earthengine-api
Requires-Dist: fiona
Requires-Dist: gdown
Requires-Dist: geemap
Requires-Dist: geopandas
Requires-Dist: geopy
Requires-Dist: ipyleaflet
Requires-Dist: joblib
Requires-Dist: lxml
Requires-Dist: matplotlib
Requires-Dist: nbformat
Requires-Dist: netCDF4
Requires-Dist: numba
Requires-Dist: numpy
Requires-Dist: osmnx
Requires-Dist: overturemaps
Requires-Dist: pandas
Requires-Dist: plotly
Requires-Dist: protobuf
Requires-Dist: py-vox-io
Requires-Dist: pycountry
Requires-Dist: pyproj
Requires-Dist: pyvista
Requires-Dist: rasterio (>=1.3.11)
Requires-Dist: requests
Requires-Dist: reverse_geocoder
Requires-Dist: rio-cogeo
Requires-Dist: rtree
Requires-Dist: scikit-learn
Requires-Dist: scipy
Requires-Dist: seaborn
Requires-Dist: shapely
Requires-Dist: taichi ; extra == "gpu"
Requires-Dist: timezonefinder
Requires-Dist: tqdm
Requires-Dist: trimesh
Requires-Dist: typer
Requires-Dist: xarray
Project-URL: bugs, https://github.com/kunifujiwara/voxcity/issues
Project-URL: changelog, https://github.com/kunifujiwara/voxcity/blob/master/changelog.md
Project-URL: homepage, https://github.com/kunifujiwara/voxcity
